django_babel/__init__.py
django_babel/extract.py
django_babel/middleware.py
django_babel/management/__init__.py
django_babel/management/commands/__init__.py
django_babel/management/commands/babel.py
django_babel/templatetags/__init__.py
django_babel/templatetags/babel.py
django_babel-0.6.1.dist-info/DESCRIPTION.rst
django_babel-0.6.1.dist-info/METADATA
django_babel-0.6.1.dist-info/RECORD
django_babel-0.6.1.dist-info/WHEEL
django_babel-0.6.1.dist-info/entry_points.txt
django_babel-0.6.1.dist-info/metadata.json
django_babel-0.6.1.dist-info/top_level.txt
